pygame_tool_kit/__init__.py
pygame_tool_kit/buttons.py
pygame_tool_kit/config.py
pygame_tool_kit/constants.py
pygame_tool_kit/delta_time.py
pygame_tool_kit/display.py
pygame_tool_kit/events_manager.py
pygame_tool_kit/kernel.py
pygame_tool_kit/keyboard.py
pygame_tool_kit/mouse.py
pygame_tool_kit/scenes.py
pygame_tool_kit/sources.py
pygame_tool_kit/storage_manager.py
Pygame_Tool_Kit-1.3.0.dist-info/LICENSE
Pygame_Tool_Kit-1.3.0.dist-info/METADATA
Pygame_Tool_Kit-1.3.0.dist-info/WHEEL
Pygame_Tool_Kit-1.3.0.dist-info/top_level.txt
Pygame_Tool_Kit-1.3.0.dist-info/RECORD
