Metadata-Version: 2.1
Name: Pygame_Tool_Kit
Version: 1.3.0
Summary: Un conjunto de herramientas útiles para el desarrollo de videojuegos con Pygame.
Home-page: https://github.com/gloacking/Pygame_Tool_Kit
Author: Gloacking
Classifier: Programming Language :: Python :: 3
Classifier: License :: OSI Approved :: MIT License
Classifier: Operating System :: OS Independent
Requires-Python: >=3.10
License-File: LICENSE
Requires-Dist: pygame
Requires-Dist: py-simple-select
